python_outreach/__init__.py
python_outreach/client.py
python_outreach/exception.py
python_outreach-0.1.5.dist-info/METADATA
python_outreach-0.1.5.dist-info/WHEEL
python_outreach-0.1.5.dist-info/entry_points.txt
python_outreach-0.1.5.dist-info/top_level.txt
python_outreach-0.1.5.dist-info/RECORD
